{
  "users": [
    {
      "username": "basset",
      "password": "$2a$08$W.qHEMAOkKjWJssi9vkOFuFjtX.156enJhvzaCPYxpDZV9Cod7HJ2"
    },
    {
      "username": "ميليسا",
      "password": "$2a$08$CxFTl3/8i8vJ9COOkS7s0OQQ/N.FPwaBzhhQLRSs379DH.7VUZmGK"
    },
    {
      "username": "زياد عبد الرحمان عزيز",
      "password": "$2a$08$OB2GvfKH3VA0r80Ud/Qrg.4IVdwdP7YmAVotje5eXB4DY5sKiqu0y"
    },
    {
      "username": "بيداري نوح",
      "password": "$2a$08$1O58jqsCPXY35PchSu8Pm.NEiqXBw3ftJA69hgU2qKxEoG8C151/m"
    }
  ]
}